{"inputs":{"node_modules/@remix-run/dev/dist/config/defaults/entry.server.node.tsx":{"bytes":4237,"imports":[{"path":"node:stream","kind":"import-statement","external":true},{"path":"@remix-run/node","kind":"import-statement","external":true},{"path":"@remix-run/react","kind":"import-statement","external":true},{"path":"isbot","kind":"import-statement","external":true},{"path":"react-dom/server","kind":"import-statement","external":true},{"path":"react/jsx-dev-runtime","kind":"import-statement","external":true}],"format":"esm"},"app/styles/tailwind.css":{"bytes":71605,"imports":[]},"app/components/Navbar.tsx":{"bytes":4038,"imports":[{"path":"react","kind":"import-statement","external":true},{"path":"@remix-run/react","kind":"import-statement","external":true},{"path":"react/jsx-dev-runtime","kind":"import-statement","external":true}],"format":"esm"},"app/components/Footer.tsx":{"bytes":2108,"imports":[{"path":"@remix-run/react","kind":"import-statement","external":true},{"path":"react/jsx-dev-runtime","kind":"import-statement","external":true}],"format":"esm"},"app/root.tsx":{"bytes":2067,"imports":[{"path":"react","kind":"import-statement","external":true},{"path":"@remix-run/react","kind":"import-statement","external":true},{"path":"framer-motion","kind":"import-statement","external":true},{"path":"app/styles/tailwind.css","kind":"import-statement","original":"./styles/tailwind.css"},{"path":"app/components/Navbar.tsx","kind":"import-statement","original":"~/components/Navbar"},{"path":"app/components/Footer.tsx","kind":"import-statement","original":"~/components/Footer"},{"path":"react/jsx-dev-runtime","kind":"import-statement","external":true}],"format":"esm"},"app/components/FAQSection.tsx":{"bytes":745,"imports":[{"path":"react","kind":"import-statement","external":true},{"path":"react/jsx-dev-runtime","kind":"import-statement","external":true}],"format":"esm"},"app/routes/services.social-media-management.tsx":{"bytes":7602,"imports":[{"path":"react","kind":"import-statement","external":true},{"path":"@remix-run/react","kind":"import-statement","external":true},{"path":"framer-motion","kind":"import-statement","external":true},{"path":"app/components/FAQSection.tsx","kind":"import-statement","original":"~/components/FAQSection"},{"path":"react/jsx-dev-runtime","kind":"import-statement","external":true}],"format":"esm"},"app/routes/services.business-citations.tsx":{"bytes":7624,"imports":[{"path":"react","kind":"import-statement","external":true},{"path":"@remix-run/react","kind":"import-statement","external":true},{"path":"framer-motion","kind":"import-statement","external":true},{"path":"app/components/FAQSection.tsx","kind":"import-statement","original":"~/components/FAQSection"},{"path":"react/jsx-dev-runtime","kind":"import-statement","external":true}],"format":"esm"},"app/routes/services.digital-services.tsx":{"bytes":6279,"imports":[{"path":"react","kind":"import-statement","external":true},{"path":"@remix-run/react","kind":"import-statement","external":true},{"path":"framer-motion","kind":"import-statement","external":true},{"path":"app/components/FAQSection.tsx","kind":"import-statement","original":"~/components/FAQSection"},{"path":"react/jsx-dev-runtime","kind":"import-statement","external":true}],"format":"esm"},"app/routes/services.website-creation.tsx":{"bytes":6545,"imports":[{"path":"react","kind":"import-statement","external":true},{"path":"@remix-run/react","kind":"import-statement","external":true},{"path":"framer-motion","kind":"import-statement","external":true},{"path":"app/components/FAQSection.tsx","kind":"import-statement","original":"~/components/FAQSection"},{"path":"react/jsx-dev-runtime","kind":"import-statement","external":true}],"format":"esm"},"app/routes/services.website-ranking.tsx":{"bytes":6041,"imports":[{"path":"react","kind":"import-statement","external":true},{"path":"@remix-run/react","kind":"import-statement","external":true},{"path":"framer-motion","kind":"import-statement","external":true},{"path":"app/components/FAQSection.tsx","kind":"import-statement","original":"~/components/FAQSection"},{"path":"react/jsx-dev-runtime","kind":"import-statement","external":true}],"format":"esm"},"app/routes/services.website-renting.tsx":{"bytes":5407,"imports":[{"path":"react","kind":"import-statement","external":true},{"path":"@remix-run/react","kind":"import-statement","external":true},{"path":"framer-motion","kind":"import-statement","external":true},{"path":"app/components/FAQSection.tsx","kind":"import-statement","original":"~/components/FAQSection"},{"path":"react/jsx-dev-runtime","kind":"import-statement","external":true}],"format":"esm"},"app/routes/services.facebook-ads.tsx":{"bytes":6354,"imports":[{"path":"react","kind":"import-statement","external":true},{"path":"@remix-run/react","kind":"import-statement","external":true},{"path":"framer-motion","kind":"import-statement","external":true},{"path":"app/components/FAQSection.tsx","kind":"import-statement","original":"~/components/FAQSection"},{"path":"react/jsx-dev-runtime","kind":"import-statement","external":true}],"format":"esm"},"app/routes/services.gbp-ranking.tsx":{"bytes":5951,"imports":[{"path":"react","kind":"import-statement","external":true},{"path":"@remix-run/react","kind":"import-statement","external":true},{"path":"framer-motion","kind":"import-statement","external":true},{"path":"app/components/FAQSection.tsx","kind":"import-statement","original":"~/components/FAQSection"},{"path":"react/jsx-dev-runtime","kind":"import-statement","external":true}],"format":"esm"},"app/routes/services.google-ads.tsx":{"bytes":7590,"imports":[{"path":"react","kind":"import-statement","external":true},{"path":"@remix-run/react","kind":"import-statement","external":true},{"path":"framer-motion","kind":"import-statement","external":true},{"path":"app/components/FAQSection.tsx","kind":"import-statement","original":"~/components/FAQSection"},{"path":"react/jsx-dev-runtime","kind":"import-statement","external":true}],"format":"esm"},"app/routes/blog.$postId.tsx":{"bytes":2437,"imports":[{"path":"react","kind":"import-statement","external":true},{"path":"@remix-run/node","kind":"import-statement","external":true},{"path":"@remix-run/react","kind":"import-statement","external":true},{"path":"react/jsx-dev-runtime","kind":"import-statement","external":true}],"format":"esm"},"app/components/BlogSearch.tsx":{"bytes":1192,"imports":[{"path":"react","kind":"import-statement","external":true},{"path":"@remix-run/react","kind":"import-statement","external":true},{"path":"react/jsx-dev-runtime","kind":"import-statement","external":true}],"format":"esm"},"app/routes/blog._index.tsx":{"bytes":3126,"imports":[{"path":"react","kind":"import-statement","external":true},{"path":"@remix-run/node","kind":"import-statement","external":true},{"path":"@remix-run/react","kind":"import-statement","external":true},{"path":"app/components/BlogSearch.tsx","kind":"import-statement","original":"~/components/BlogSearch"},{"path":"react/jsx-dev-runtime","kind":"import-statement","external":true}],"format":"esm"},"app/routes/contact.tsx":{"bytes":4025,"imports":[{"path":"react","kind":"import-statement","external":true},{"path":"@remix-run/node","kind":"import-statement","external":true},{"path":"@remix-run/react","kind":"import-statement","external":true},{"path":"@prisma/client","kind":"import-statement","external":true},{"path":"nodemailer","kind":"import-statement","external":true},{"path":"react/jsx-dev-runtime","kind":"import-statement","external":true}],"format":"esm"},"app/components/JsonLd.tsx":{"bytes":524,"imports":[{"path":"react","kind":"import-statement","external":true},{"path":"@remix-run/react","kind":"import-statement","external":true},{"path":"react/jsx-dev-runtime","kind":"import-statement","external":true}],"format":"esm"},"app/components/Testimonials.tsx":{"bytes":1715,"imports":[{"path":"react","kind":"import-statement","external":true},{"path":"framer-motion","kind":"import-statement","external":true},{"path":"react/jsx-dev-runtime","kind":"import-statement","external":true}],"format":"esm"},"app/components/PricingCalculator.tsx":{"bytes":2558,"imports":[{"path":"react","kind":"import-statement","external":true},{"path":"react/jsx-dev-runtime","kind":"import-statement","external":true}],"format":"esm"},"app/components/NewsletterSignup.tsx":{"bytes":1565,"imports":[{"path":"react","kind":"import-statement","external":true},{"path":"@remix-run/react","kind":"import-statement","external":true},{"path":"react/jsx-dev-runtime","kind":"import-statement","external":true}],"format":"esm"},"app/routes/_index.tsx":{"bytes":6259,"imports":[{"path":"react","kind":"import-statement","external":true},{"path":"@remix-run/node","kind":"import-statement","external":true},{"path":"@remix-run/react","kind":"import-statement","external":true},{"path":"framer-motion","kind":"import-statement","external":true},{"path":"app/components/JsonLd.tsx","kind":"import-statement","original":"~/components/JsonLd"},{"path":"app/components/Testimonials.tsx","kind":"import-statement","original":"~/components/Testimonials"},{"path":"app/components/PricingCalculator.tsx","kind":"import-statement","original":"~/components/PricingCalculator"},{"path":"app/components/NewsletterSignup.tsx","kind":"import-statement","original":"~/components/NewsletterSignup"},{"path":"react/jsx-dev-runtime","kind":"import-statement","external":true}],"format":"esm"},"app/routes/about.tsx":{"bytes":3898,"imports":[{"path":"framer-motion","kind":"import-statement","external":true},{"path":"app/components/JsonLd.tsx","kind":"import-statement","original":"~/components/JsonLd"},{"path":"react/jsx-dev-runtime","kind":"import-statement","external":true}],"format":"esm"},"server-assets-manifest:@remix-run/dev/assets-manifest":{"bytes":5979,"imports":[],"format":"esm"},"server-entry-module:@remix-run/dev/server-build":{"bytes":4709,"imports":[{"path":"node_modules/@remix-run/dev/dist/config/defaults/entry.server.node.tsx","kind":"import-statement","original":"/Users/devintripp/Desktop/Peak Growth Digital LLC/PGDWebsiteFiles/peak_growth_digital/node_modules/@remix-run/dev/dist/config/defaults/entry.server.node.tsx"},{"path":"app/root.tsx","kind":"import-statement","original":"./root.tsx"},{"path":"app/routes/services.social-media-management.tsx","kind":"import-statement","original":"./routes/services.social-media-management.tsx"},{"path":"app/routes/services.business-citations.tsx","kind":"import-statement","original":"./routes/services.business-citations.tsx"},{"path":"app/routes/services.digital-services.tsx","kind":"import-statement","original":"./routes/services.digital-services.tsx"},{"path":"app/routes/services.website-creation.tsx","kind":"import-statement","original":"./routes/services.website-creation.tsx"},{"path":"app/routes/services.website-ranking.tsx","kind":"import-statement","original":"./routes/services.website-ranking.tsx"},{"path":"app/routes/services.website-renting.tsx","kind":"import-statement","original":"./routes/services.website-renting.tsx"},{"path":"app/routes/services.facebook-ads.tsx","kind":"import-statement","original":"./routes/services.facebook-ads.tsx"},{"path":"app/routes/services.gbp-ranking.tsx","kind":"import-statement","original":"./routes/services.gbp-ranking.tsx"},{"path":"app/routes/services.google-ads.tsx","kind":"import-statement","original":"./routes/services.google-ads.tsx"},{"path":"app/routes/blog.$postId.tsx","kind":"import-statement","original":"./routes/blog.$postId.tsx"},{"path":"app/routes/blog._index.tsx","kind":"import-statement","original":"./routes/blog._index.tsx"},{"path":"app/routes/contact.tsx","kind":"import-statement","original":"./routes/contact.tsx"},{"path":"app/routes/_index.tsx","kind":"import-statement","original":"./routes/_index.tsx"},{"path":"app/routes/about.tsx","kind":"import-statement","original":"./routes/about.tsx"},{"path":"server-assets-manifest:@remix-run/dev/assets-manifest","kind":"import-statement","original":"@remix-run/dev/assets-manifest"}],"format":"esm"},"<stdin>":{"bytes":44,"imports":[{"path":"server-entry-module:@remix-run/dev/server-build","kind":"import-statement","original":"@remix-run/dev/server-build"}],"format":"esm"}},"outputs":{"build/_assets/tailwind-3QOVAR2H.css":{"imports":[],"exports":[],"inputs":{"app/styles/tailwind.css":{"bytesInOutput":71605}},"bytes":71605},"build/index.js.map":{"imports":[],"exports":[],"inputs":{},"bytes":184019},"build/index.js":{"imports":[{"path":"node:stream","kind":"import-statement","external":true},{"path":"@remix-run/node","kind":"import-statement","external":true},{"path":"@remix-run/react","kind":"import-statement","external":true},{"path":"isbot","kind":"import-statement","external":true},{"path":"react-dom/server","kind":"import-statement","external":true},{"path":"react/jsx-dev-runtime","kind":"import-statement","external":true},{"path":"@remix-run/react","kind":"import-statement","external":true},{"path":"framer-motion","kind":"import-statement","external":true},{"path":"build/_assets/tailwind-3QOVAR2H.css","kind":"file-loader"},{"path":"react","kind":"import-statement","external":true},{"path":"@remix-run/react","kind":"import-statement","external":true},{"path":"react/jsx-dev-runtime","kind":"import-statement","external":true},{"path":"@remix-run/react","kind":"import-statement","external":true},{"path":"react/jsx-dev-runtime","kind":"import-statement","external":true},{"path":"react/jsx-dev-runtime","kind":"import-statement","external":true},{"path":"@remix-run/react","kind":"import-statement","external":true},{"path":"framer-motion","kind":"import-statement","external":true},{"path":"react/jsx-dev-runtime","kind":"import-statement","external":true},{"path":"react/jsx-dev-runtime","kind":"import-statement","external":true},{"path":"@remix-run/react","kind":"import-statement","external":true},{"path":"framer-motion","kind":"import-statement","external":true},{"path":"react/jsx-dev-runtime","kind":"import-statement","external":true},{"path":"@remix-run/react","kind":"import-statement","external":true},{"path":"framer-motion","kind":"import-statement","external":true},{"path":"react/jsx-dev-runtime","kind":"import-statement","external":true},{"path":"@remix-run/react","kind":"import-statement","external":true},{"path":"framer-motion","kind":"import-statement","external":true},{"path":"react/jsx-dev-runtime","kind":"import-statement","external":true},{"path":"@remix-run/react","kind":"import-statement","external":true},{"path":"framer-motion","kind":"import-statement","external":true},{"path":"react/jsx-dev-runtime","kind":"import-statement","external":true},{"path":"@remix-run/react","kind":"import-statement","external":true},{"path":"framer-motion","kind":"import-statement","external":true},{"path":"react/jsx-dev-runtime","kind":"import-statement","external":true},{"path":"@remix-run/react","kind":"import-statement","external":true},{"path":"framer-motion","kind":"import-statement","external":true},{"path":"react/jsx-dev-runtime","kind":"import-statement","external":true},{"path":"@remix-run/react","kind":"import-statement","external":true},{"path":"framer-motion","kind":"import-statement","external":true},{"path":"react/jsx-dev-runtime","kind":"import-statement","external":true},{"path":"@remix-run/react","kind":"import-statement","external":true},{"path":"framer-motion","kind":"import-statement","external":true},{"path":"react/jsx-dev-runtime","kind":"import-statement","external":true},{"path":"@remix-run/node","kind":"import-statement","external":true},{"path":"@remix-run/react","kind":"import-statement","external":true},{"path":"react/jsx-dev-runtime","kind":"import-statement","external":true},{"path":"@remix-run/node","kind":"import-statement","external":true},{"path":"@remix-run/react","kind":"import-statement","external":true},{"path":"react","kind":"import-statement","external":true},{"path":"@remix-run/react","kind":"import-statement","external":true},{"path":"react/jsx-dev-runtime","kind":"import-statement","external":true},{"path":"react/jsx-dev-runtime","kind":"import-statement","external":true},{"path":"@remix-run/node","kind":"import-statement","external":true},{"path":"@remix-run/react","kind":"import-statement","external":true},{"path":"@prisma/client","kind":"import-statement","external":true},{"path":"react/jsx-dev-runtime","kind":"import-statement","external":true},{"path":"@remix-run/node","kind":"import-statement","external":true},{"path":"@remix-run/react","kind":"import-statement","external":true},{"path":"framer-motion","kind":"import-statement","external":true},{"path":"@remix-run/react","kind":"import-statement","external":true},{"path":"react/jsx-dev-runtime","kind":"import-statement","external":true},{"path":"framer-motion","kind":"import-statement","external":true},{"path":"react/jsx-dev-runtime","kind":"import-statement","external":true},{"path":"react","kind":"import-statement","external":true},{"path":"react/jsx-dev-runtime","kind":"import-statement","external":true},{"path":"react","kind":"import-statement","external":true},{"path":"@remix-run/react","kind":"import-statement","external":true},{"path":"react/jsx-dev-runtime","kind":"import-statement","external":true},{"path":"react/jsx-dev-runtime","kind":"import-statement","external":true},{"path":"framer-motion","kind":"import-statement","external":true},{"path":"react/jsx-dev-runtime","kind":"import-statement","external":true}],"exports":["assets","assetsBuildDirectory","entry","future","mode","publicPath","routes"],"entryPoint":"<stdin>","inputs":{"node_modules/@remix-run/dev/dist/config/defaults/entry.server.node.tsx":{"bytesInOutput":3512},"app/root.tsx":{"bytesInOutput":5166},"app/styles/tailwind.css":{"bytesInOutput":63},"app/components/Navbar.tsx":{"bytesInOutput":9868},"app/components/Footer.tsx":{"bytesInOutput":5156},"app/routes/services.social-media-management.tsx":{"bytesInOutput":15612},"app/components/FAQSection.tsx":{"bytesInOutput":1654},"app/routes/services.business-citations.tsx":{"bytesInOutput":15081},"app/routes/services.digital-services.tsx":{"bytesInOutput":12423},"app/routes/services.website-creation.tsx":{"bytesInOutput":12741},"app/routes/services.website-ranking.tsx":{"bytesInOutput":11834},"app/routes/services.website-renting.tsx":{"bytesInOutput":11200},"app/routes/services.facebook-ads.tsx":{"bytesInOutput":12438},"app/routes/services.gbp-ranking.tsx":{"bytesInOutput":11136},"app/routes/services.google-ads.tsx":{"bytesInOutput":14684},"app/routes/blog.$postId.tsx":{"bytesInOutput":2735},"app/routes/blog._index.tsx":{"bytesInOutput":4809},"app/components/BlogSearch.tsx":{"bytesInOutput":2158},"app/routes/contact.tsx":{"bytesInOutput":7037},"app/routes/_index.tsx":{"bytesInOutput":11993},"app/components/JsonLd.tsx":{"bytesInOutput":600},"app/components/Testimonials.tsx":{"bytesInOutput":2641},"app/components/PricingCalculator.tsx":{"bytesInOutput":5640},"app/components/NewsletterSignup.tsx":{"bytesInOutput":3235},"app/routes/about.tsx":{"bytesInOutput":8023},"server-assets-manifest:@remix-run/dev/assets-manifest":{"bytesInOutput":5737},"server-entry-module:@remix-run/dev/server-build":{"bytesInOutput":3460},"<stdin>":{"bytesInOutput":0}},"bytes":202134}}}